calitp_littlepay-2025.4.1.dist-info/licenses/LICENSE
littlepay/__init__.py
littlepay/config.py
littlepay/main.py
littlepay/api/__init__.py
littlepay/api/card_tokenization.py
littlepay/api/client.py
littlepay/api/funding_sources.py
littlepay/api/groups.py
littlepay/api/products.py
littlepay/commands/__init__.py
littlepay/commands/configure.py
littlepay/commands/groups.py
littlepay/commands/products.py
littlepay/commands/switch.py
calitp_littlepay-2025.4.1.dist-info/METADATA
calitp_littlepay-2025.4.1.dist-info/WHEEL
calitp_littlepay-2025.4.1.dist-info/entry_points.txt
calitp_littlepay-2025.4.1.dist-info/top_level.txt
calitp_littlepay-2025.4.1.dist-info/RECORD
