Metadata-Version: 2.4
Name: calitp-littlepay
Version: 2025.4.1
Summary: Cal-ITP API implementations and admin tasks for Littlepay.
Maintainer-email: Compiler LLC <dev@compiler.la>
License:                                  Apache License
Project-URL: Changelog, https://github.com/cal-itp/littlepay/releases
Project-URL: Code, https://github.com/cal-itp/littlepay
Project-URL: Issues, https://github.com/cal-itp/littlepay/issues
Classifier: Programming Language :: Python :: 3 :: Only
Requires-Python: >=3.10
License-File: LICENSE
Requires-Dist: Authlib>=1.2.1
Requires-Dist: PyYAML>=6.0.1
Requires-Dist: requests>=2.31.0
Provides-Extra: dev
Requires-Dist: black; extra == "dev"
Requires-Dist: build; extra == "dev"
Requires-Dist: flake8; extra == "dev"
Requires-Dist: pre-commit; extra == "dev"
Requires-Dist: setuptools_scm; extra == "dev"
Provides-Extra: test
Requires-Dist: coverage; extra == "test"
Requires-Dist: pytest; extra == "test"
Requires-Dist: pytest-mock; extra == "test"
Requires-Dist: pytest-socket; extra == "test"
Dynamic: license-file
